MANIFEST.in
README.txt
setup.cfg
setup.py
csci/__init__.py
csci.tweetsite.egg-info/PKG-INFO
csci.tweetsite.egg-info/SOURCES.txt
csci.tweetsite.egg-info/dependency_links.txt
csci.tweetsite.egg-info/entry_points.txt
csci.tweetsite.egg-info/namespace_packages.txt
csci.tweetsite.egg-info/not-zip-safe
csci.tweetsite.egg-info/paster_plugins.txt
csci.tweetsite.egg-info/requires.txt
csci.tweetsite.egg-info/top_level.txt
csci/tweetsite/README.txt
csci/tweetsite/__init__.py
csci/tweetsite/config.py
csci/tweetsite/configure.zcml
csci/tweetsite/form.py
csci/tweetsite/browser/__init__.py
csci/tweetsite/browser/configure.zcml
csci/tweetsite/browser/controlpaneladd.py
csci/tweetsite/browser/controlpanelupdateview.pt
csci/tweetsite/browser/controlpanelupdateview.py
csci/tweetsite/browser/controlpanelview.pt
csci/tweetsite/browser/controlpanelview.py
csci/tweetsite/browser/onlinefeedview.pt
csci/tweetsite/browser/onlinefeedview.py
csci/tweetsite/browser/tweetfolderview.pt
csci/tweetsite/browser/tweetfolderview.py
csci/tweetsite/browser/lib/__init__.py
csci/tweetsite/browser/lib/feedparser.py
csci/tweetsite/browser/lib/google_short.py
csci/tweetsite/browser/lib/twitter.py
csci/tweetsite/browser/lib/wwpLib.py
csci/tweetsite/content/__init__.py
csci/tweetsite/content/configure.zcml
csci/tweetsite/content/controlpanel.py
csci/tweetsite/content/onlinefeed.py
csci/tweetsite/content/tweetfolder.py
csci/tweetsite/interfaces/__init__.py
csci/tweetsite/interfaces/controlpanel.py
csci/tweetsite/interfaces/onlinefeed.py
csci/tweetsite/interfaces/tweetfolder.py
csci/tweetsite/portlets/__init__.py
csci/tweetsite/portlets/configure.zcml
csci/tweetsite/profiles/default/factorytool.xml
csci/tweetsite/profiles/default/metadata.xml
csci/tweetsite/profiles/default/portlets.xml
csci/tweetsite/profiles/default/rolemap.xml
csci/tweetsite/profiles/default/types.xml
csci/tweetsite/profiles/default/types/controlPanel.xml
csci/tweetsite/profiles/default/types/onlineFeed.xml
csci/tweetsite/profiles/default/types/tweetfolder.xml
csci/tweetsite/tests/__init__.py
csci/tweetsite/tests/base.py
csci/tweetsite/tests/test_doctest.py