Metadata-Version: 1.0
Name: csci.tweetsite
Version: 1.1
Summary: UNKNOWN
Home-page: http://svn.plone.org/svn/plone/plone.example
Author: Plone Foundation
Author-email: plone-developers@lists.sourceforge.net
License: GPL
Platform: UNKNOWN
Classifier: Framework :: Plone
Classifier: Intended Audience :: Developers
Classifier: License :: OSI Approved :: GNU General Public License (GPL)
